openai_tools/__init__.py
openai_tools/prompt.py
openai_tools/utils.py
openai_tools-0.0.0.1.dist-info/LICENSE
openai_tools-0.0.0.1.dist-info/METADATA
openai_tools-0.0.0.1.dist-info/WHEEL
openai_tools-0.0.0.1.dist-info/top_level.txt
openai_tools-0.0.0.1.dist-info/RECORD
