Metadata-Version: 2.1
Name: openai-tools
Version: 0.0.0.1
Summary: A Python wrapper for managing OpenAI API.
Author-email: "Aivin V. Solatorio" <avsolatorio@gmail.com>
Maintainer-email: "Aivin V. Solatorio" <avsolatorio@gmail.com>
License: MIT License
Project-URL: Homepage, https://github.com/avsolatorio/gpt-tools
Project-URL: Bug Reports, https://github.com/avsolatorio/gpt-tools/issues
Project-URL: Source, https://github.com/avsolatorio/gpt-tools
Keywords: gpt tools,openai,gpt3,metadata,augmentation,data,data augmentation
Classifier: Programming Language :: Python :: 3
Classifier: Programming Language :: Python :: 3.10
Classifier: Programming Language :: Python :: 3.11
Classifier: Programming Language :: Python :: 3 :: Only
Classifier: Intended Audience :: Developers
Classifier: Operating System :: OS Independent
Requires-Python: >=3.10
Provides-Extra: notebook
License-File: LICENSE
